Task2 Codes/boolean_logic.v
module boolean_logic (
    input A, B, C, D,
    output Y
);
    assign Y = (A & B) | (~C & D);
endmodule

Task2 Codes/tb_boolean_logic.v
`timescale 1ns / 1ps

module tb_boolean_logic;
    reg A, B, C, D;
    wire Y;
    
    // Declare the integer here, outside the initial block
    integer i;

    // Instantiate the Boolean Logic Module
    boolean_logic uut (
        .A(A),
        .B(B),
        .C(C),
        .D(D),
        .Y(Y)
    );

    initial begin
        // --- Waveform setup ---
        $dumpfile("bool_output.vcd");
        $dumpvars(0, tb_boolean_logic);
        
        // Header
        $display("A B C D | Y");
        $display("-----------");
        $monitor("%b %b %b %b | %b", A, B, C, D, Y);
        
        // Stimulus - iterating through all 16 combinations
        for (i = 0; i < 16; i = i + 1) begin
            {A, B, C, D} = i;
            #10;
        end
        
        $finish;
    end
endmodule

Task2 Codes/bool_output.vcd
$date
	Tue Apr 21 14:38:08 2026
$end
$version
	Icarus Verilog
$end
$timescale
	1ps
$end
$scope module tb_boolean_logic $end
$var wire 1 ! Y $end
$var reg 1 " A $end
$var reg 1 # B $end
$var reg 1 $ C $end
$var reg 1 % D $end
$var integer 32 & i [31:0] $end
$scope module uut $end
$var wire 1 " A $end
$var wire 1 # B $end
$var wire 1 $ C $end
$var wire 1 % D $end
$var wire 1 ! Y $end
$upscope $end
$upscope $end
$enddefinitions $end
$comment Show the parameter values. $end
$dumpall
$end
#0
$dumpvars
b0 &
0%
0$
0#
0"
0!
$end
#10000
1!
1%
b1 &
#20000
0!
1$
0%
b10 &
#30000
1%
b11 &
#40000
1#
0$
0%
b100 &
#50000
1!
1%
b101 &
#60000
0!
1$
0%
b110 &
#70000
1%
b111 &
#80000
1"
0#
0$
0%
b1000 &
#90000
1!
1%
b1001 &
#100000
0!
1$
0%
b1010 &
#110000
1%
b1011 &
#120000
1!
1#
0$
0%
b1100 &
#130000
1%
b1101 &
#140000
1$
0%
b1110 &
#150000
1%
b1111 &
#160000
b10000 &
