Task2 Codes/half_adder.v
module half_adder (
    input A, B,
    output Sum, Carry
);
    assign Sum   = A ^ B;    // XOR gate
    assign Carry = A & B;    // AND gate
endmodule

Task2 Codes/full_adder.v
module full_adder (
    input A, B, Cin,
    output Sum, Cout
);
    wire s1, c1, c2;

    // Structural modeling using half adders
    half_adder HA1 (.A(A), .B(B), .Sum(s1), .Carry(c1));
    half_adder HA2 (.A(s1), .B(Cin), .Sum(Sum), .Carry(c2));
    
    assign Cout = c1 | c2; // Logic: C_out = (A&B) | (Cin&(A^B))
endmodule

Task2 Codes/tb_full_adder.v
`timescale 1ns / 1ps

module tb_full_adder;
    // Signals to drive the full adder
    reg A, B, Cin;
    wire Sum, Cout;

    // Instantiate the Full Adder
    full_adder uut (
        .A(A),
        .B(B),
        .Cin(Cin),
        .Sum(Sum),
        .Cout(Cout)
    );

    initial begin
        // --- Waveform setup for GTKWave ---
        $dumpfile("full_adder_output.vcd");
        $dumpvars(0, tb_full_adder);
        
        // Header for terminal output
        $display("A B Cin | Sum Cout");
        $display("------------------");
        $monitor("%b %b  %b  |  %b    %b", A, B, Cin, Sum, Cout);
        
        // Stimulus - testing all 8 combinations
        A = 0; B = 0; Cin = 0; #10;
        A = 0; B = 0; Cin = 1; #10;
        A = 0; B = 1; Cin = 0; #10;
        A = 0; B = 1; Cin = 1; #10;
        A = 1; B = 0; Cin = 0; #10;
        A = 1; B = 0; Cin = 1; #10;
        A = 1; B = 1; Cin = 0; #10;
        A = 1; B = 1; Cin = 1; #10;
        
        $finish;
    end
endmodule

Task2 Codes/full_adder_output.vcd
$date
	Tue Apr 21 14:30:09 2026
$end
$version
	Icarus Verilog
$end
$timescale
	1ps
$end
$scope module tb_full_adder $end
$var wire 1 ! Sum $end
$var wire 1 " Cout $end
$var reg 1 # A $end
$var reg 1 $ B $end
$var reg 1 % Cin $end
$scope module uut $end
$var wire 1 # A $end
$var wire 1 $ B $end
$var wire 1 % Cin $end
$var wire 1 " Cout $end
$var wire 1 & s1 $end
$var wire 1 ' c2 $end
$var wire 1 ( c1 $end
$var wire 1 ! Sum $end
$scope module HA1 $end
$var wire 1 # A $end
$var wire 1 $ B $end
$var wire 1 ( Carry $end
$var wire 1 & Sum $end
$upscope $end
$scope module HA2 $end
$var wire 1 & A $end
$var wire 1 % B $end
$var wire 1 ' Carry $end
$var wire 1 ! Sum $end
$upscope $end
$upscope $end
$upscope $end
$enddefinitions $end
$comment Show the parameter values. $end
$dumpall
$end
#0
$dumpvars
0(
0'
0&
0%
0$
0#
0"
0!
$end
#10000
1!
1%
#20000
1&
0%
1$
#30000
1"
0!
1'
1%
#40000
0"
1!
0'
0%
0$
1#
#50000
1"
0!
1'
1%
#60000
0'
0&
1(
0%
1$
#70000
1!
1%
